setup.py
aros/__init__.py
aros/core.py
aros/node.py
aros.egg-info/PKG-INFO
aros.egg-info/SOURCES.txt
aros.egg-info/dependency_links.txt
aros.egg-info/top_level.txt
aros/test/__init__.py