Metadata-Version: 1.0
Name: aros
Version: 0.0.3
Summary: A Python Robot Operating System
Home-page: http://roboyun.com
Author: Liu Peng
Author-email: UNKNOWN
License: BSD
Platform: UNKNOWN
